{
  "version": "pro-hybrid-confluence-v6.3",
  "architecture_version": "HYBRID_CONFLUENCE_V6_3",
  "signals": [
    {
      "id": "b28603943c",
      "time": "2026-06-21T19:42:37.627216+00:00",
      "action": "NO_SETUP",
      "side": "LONG",
      "setup_type": "PULLBACK_CONTINUATION",
      "quality": 52,
      "reason": "Професійний сетап не пройшов gate'и якості",
      "regime": "RANGE",
      "news_bias": "NEUTRAL",
      "macro_risk": "NORMAL",
      "version": "pro-hybrid-confluence-v6.3",
      "architecture_version": "HYBRID_CONFLUENCE_V6_3"
    }
  ],
  "trades": [],
  "analytics": {
    "closed_trades": 0,
    "wins": 0,
    "losses": 0,
    "win_rate": 0.0,
    "net_r": 0.0,
    "expectancy_r": 0.0,
    "by_family": {}
  },
  "updated_at": "2026-06-21T19:42:37.963951+00:00"
}