{
  "signals": [
    {
      "id": "44954a9c5f",
      "time": "2026-06-21T20:54:30.766775+00:00",
      "action": "NO_SETUP",
      "side": "LONG",
      "setup_type": "PULLBACK_CONTINUATION",
      "quality": 52,
      "reason": "Професійний сетап не пройшов gate'и якості",
      "regime": "RANGE",
      "news_bias": "NEUTRAL",
      "macro_risk": "NORMAL",
      "version": "pro-hybrid-confluence-v6.4",
      "architecture_version": "HYBRID_CONFLUENCE_V6_4"
    },
    {
      "id": "e8e4111c9d",
      "time": "2026-06-21T21:01:02.198236+00:00",
      "action": "RISKY_ENTRY",
      "side": "SHORT",
      "setup_type": "PULLBACK_CONTINUATION",
      "quality": 71,
      "reason": "Ризикований ранній вхід: Продовження тренду після ICT-відкату — B gate v6",
      "regime": "TRANSITION",
      "news_bias": "NEUTRAL",
      "macro_risk": "NORMAL",
      "version": "pro-hybrid-confluence-v6.4",
      "architecture_version": "HYBRID_CONFLUENCE_V6_4"
    },
    {
      "time": "2026-06-21T21:03:01.500194+00:00",
      "type": "FOLLOW",
      "action": "HOLD",
      "side": "SHORT",
      "price": 82.13
    },
    {
      "time": "2026-06-21T21:15:45.897504+00:00",
      "type": "FOLLOW",
      "action": "HOLD",
      "side": "SHORT",
      "price": 81.8
    },
    {
      "time": "2026-06-21T21:21:32.344662+00:00",
      "type": "FOLLOW",
      "action": "HOLD",
      "side": "SHORT",
      "price": 81.97
    },
    {
      "time": "2026-06-21T21:29:22.062555+00:00",
      "type": "FOLLOW",
      "action": "HOLD",
      "side": "SHORT",
      "price": 82.19
    },
    {
      "time": "2026-06-21T21:31:01.652980+00:00",
      "type": "FOLLOW",
      "action": "HOLD",
      "side": "SHORT",
      "price": 82.2
    },
    {
      "time": "2026-06-21T21:36:17.376215+00:00",
      "type": "FOLLOW",
      "action": "STOP",
      "side": "SHORT",
      "price": 82.77
    },
    {
      "id": "12730bda2b",
      "time": "2026-06-21T21:38:57.221124+00:00",
      "action": "ARMED",
      "side": "LONG",
      "setup_type": "PULLBACK_CONTINUATION",
      "quality": 62,
      "reason": "Продовження тренду після ICT-відкату сформовано; gate v6: WATCH | NORMAL",
      "regime": "TRANSITION",
      "news_bias": "NEUTRAL",
      "macro_risk": "NORMAL",
      "version": "pro-hybrid-confluence-v6.4",
      "architecture_version": "HYBRID_CONFLUENCE_V6_4"
    },
    {
      "id": "71dc4fb73e",
      "time": "2026-06-21T21:45:45.989444+00:00",
      "action": "ARMED",
      "side": "SHORT",
      "setup_type": "PULLBACK_CONTINUATION",
      "quality": 64,
      "reason": "Продовження тренду після ICT-відкату сформовано; gate v6: WATCH | NORMAL",
      "regime": "TRANSITION",
      "news_bias": "NEUTRAL",
      "macro_risk": "NORMAL",
      "version": "pro-hybrid-confluence-v6.4",
      "architecture_version": "HYBRID_CONFLUENCE_V6_4"
    }
  ],
  "trades": [
    {
      "id": "864eb4eb59",
      "side": "SHORT",
      "setup_type": "PULLBACK_CONTINUATION",
      "result_pct": -0.9636496706513685,
      "mfe_pct": 0.21956574774336038
    }
  ],
  "version": "pro-hybrid-confluence-v6.4",
  "architecture_version": "HYBRID_CONFLUENCE_V6_4",
  "analytics": {
    "closed_trades": 1,
    "wins": 0,
    "losses": 1,
    "win_rate": 0.0,
    "net_r": -0.01,
    "expectancy_r": -0.01,
    "by_family": {}
  },
  "updated_at": "2026-06-21T21:45:46.558263+00:00"
}